hawkauthlib/__init__.py
hawkauthlib/noncecache.py
hawkauthlib/utils.py
hawkauthlib/tests/__init__.py
hawkauthlib/tests/test_noncecache.py
hawkauthlib/tests/test_request_objects.py
hawkauthlib/tests/test_signatures.py
hawkauthlib/tests/test_utils.py
hawkauthlib-2.0.0.dist-info/DESCRIPTION.rst
hawkauthlib-2.0.0.dist-info/METADATA
hawkauthlib-2.0.0.dist-info/RECORD
hawkauthlib-2.0.0.dist-info/WHEEL
hawkauthlib-2.0.0.dist-info/metadata.json
hawkauthlib-2.0.0.dist-info/top_level.txt
lib/hawkauthlib/__init__.py
lib/hawkauthlib/noncecache.py
lib/hawkauthlib/utils.py
lib/hawkauthlib/tests/__init__.py
lib/hawkauthlib/tests/test_noncecache.py
lib/hawkauthlib/tests/test_request_objects.py
lib/hawkauthlib/tests/test_signatures.py
lib/hawkauthlib/tests/test_utils.py
