Metadata-Version: 2.0
Name: hawkauthlib
Version: 2.0.0
Summary: Hawk Access Authentication protocol
Home-page: https://github.com/mozilla-services/hawkauthlib
Author: Mozilla Services
Author-email: services-dev@mozilla.org
License: MPLv2.0
Keywords: authentication Hawk HTTP request signing
Platform: UNKNOWN
Classifier: Programming Language :: Python
Classifier: License :: OSI Approved :: Mozilla Public License 2.0 (MPL 2.0)
Requires-Dist: webob
Provides-Extra: test
Requires-Dist: requests; extra == 'test'
